setup.cfg
setup.py
./pythonToHtml/htmlwriter/HtmlTable.py
./pythonToHtml/htmlwriter/HtmlWriter.py
./pythonToHtml/htmlwriter/__init__.py
./pythonToHtml/htmlwriter/utils.py
./pythonToLatex/latexwriter/LatexGraph.py
./pythonToLatex/latexwriter/LatexPlot.py
./pythonToLatex/latexwriter/LatexTable.py
./pythonToLatex/latexwriter/LatexWriter.py
./pythonToLatex/latexwriter/__init__.py
./pythonToLatex/latexwriter/utils.py
./pythonToMarkdown/markdownwriter/MarkdownTable.py
./pythonToMarkdown/markdownwriter/MarkdownWriter.py
./pythonToMarkdown/markdownwriter/__init__.py
./pythonToMarkdown/pandocmarkdownwriter/PandocMarkdownTable.py
./pythonToMarkdown/pandocmarkdownwriter/PandocMarkdownWriter.py
./pythonToMarkdown/pandocmarkdownwriter/__init__.py
MarkdownWriter.egg-info/PKG-INFO
MarkdownWriter.egg-info/SOURCES.txt
MarkdownWriter.egg-info/dependency_links.txt
MarkdownWriter.egg-info/top_level.txt
tests/__init__.py
tests/test_markdownwriter.py
tests/test_pandocmarkdownwriter.py