Metadata-Version: 1.0
Name: MarkdownWriter
Version: 1.1
Summary: Markdown Writer API
Home-page: https://github.com/mikrosimage/python-markup-writer
Author: Valentin NOEL, Marc-Antoine ARNAUD
Author-email: valent.noel@gmail.com
License: UNKNOWN
Keywords: Markdown
Platform: UNKNOWN
